sysmess.cp312-win32.pyd
sysmess-0.1.5.dist-info/licenses/LICENSE
sysmess-0.1.5.dist-info/METADATA
sysmess-0.1.5.dist-info/WHEEL
sysmess-0.1.5.dist-info/top_level.txt
sysmess-0.1.5.dist-info/RECORD
