Metadata-Version: 2.4
Name: sysmess
Version: 0.1.5
Summary: Fancy terminal message box renderer using Unicode box characters and ANSI styling
Home-page: 
Author: Luke Canada
Author-email: canadaluke888@gmail.com
Classifier: Programming Language :: Python :: 3
Classifier: Programming Language :: C
Classifier: Operating System :: OS Independent
Requires-Python: >=3.6
License-File: LICENSE
Dynamic: author
Dynamic: author-email
Dynamic: classifier
Dynamic: description
Dynamic: description-content-type
Dynamic: license-file
Dynamic: requires-python
Dynamic: summary
